LICENSE
MANIFEST.in
README.rst
setup.py
django_grappelli_filters.egg-info/PKG-INFO
django_grappelli_filters.egg-info/SOURCES.txt
django_grappelli_filters.egg-info/dependency_links.txt
django_grappelli_filters.egg-info/requires.txt
django_grappelli_filters.egg-info/top_level.txt
grappelli_filters/__init__.py
grappelli_filters/admin.py
grappelli_filters/filters.py
grappelli_filters/models.py
grappelli_filters/tests.py
grappelli_filters/views.py
grappelli_filters/static/grappelli_filters/filter.css
grappelli_filters/static/grappelli_filters/filter.js
grappelli_filters/templates/.DS_Store
grappelli_filters/templates/grappelli_filters/related_autocomplete.html
grappelli_filters/templates/grappelli_filters/search.html