Metadata-Version: 1.1
Name: django-grappelli-filters
Version: 0.2.1
Summary: Additional filters for Djagno Grappelli admin
Home-page: https://github.com/frnhr/django-grappelli-filters/
Author: Fran Hrzenjak
Author-email: fran@changeset.hr
License: Unlicense
Platform: UNKNOWN
Classifier: Environment :: Web Environment
Classifier: Framework :: Django
Classifier: Intended Audience :: Developers
Classifier: License :: Freeware
Classifier: Operating System :: OS Independent
Classifier: Programming Language :: Python
Classifier: Programming Language :: Python :: 2
Classifier: Programming Language :: Python :: 2.7
Classifier: Topic :: Internet :: WWW/HTTP
Classifier: Topic :: Internet :: WWW/HTTP :: Dynamic Content
